[
  {
    "result": "W",
    "isHomeGame": false,
    "date": "09/28/1957",
    "location": {
      "city": "West Lafayette",
      "state": "IN",
      "stadium": "Ross-Ade Stadium",
      "coordinates": [40.434042, -86.918267]
    },
    "opponentId": "PUR",
    "score": {"away": 12, "home": 0},
    "linescore": {"away": [], "home": []},
    "headCoach": "Terry Brennan"
  },
  {
    "result": "W",
    "isHomeGame": true,
    "date": "10/05/1957",
    "opponentId": "IND",
    "score": {"away": 0, "home": 26},
    "linescore": {"away": [], "home": []},
    "headCoach": "Terry Brennan",
    "rankings": {"home": {"ap": 16}},
    "weather": {"icon": "clear-night", "temperature": 42}
  },
  {
    "result": "W",
    "isHomeGame": true,
    "date": "10/12/1957",
    "opponentId": "ARMY",
    "score": {"away": 21, "home": 23},
    "linescore": {"away": [], "home": []},
    "headCoach": "Terry Brennan",
    "rankings": {"home": {"ap": 12}, "away": {"ap": 10}},
    "weather": {"icon": "clear-night", "temperature": 37}
  },
  {
    "result": "W",
    "isHomeGame": true,
    "date": "10/26/1957",
    "opponentId": "PITT",
    "score": {"away": 7, "home": 13},
    "linescore": {"away": [], "home": []},
    "headCoach": "Terry Brennan",
    "rankings": {"home": {"ap": 7}},
    "weather": {"icon": "partly-cloudy-night", "temperature": 33}
  },
  {
    "result": "L",
    "isHomeGame": true,
    "date": "11/02/1957",
    "opponentId": "NAVY",
    "score": {"away": 20, "home": 6},
    "linescore": {"away": [], "home": []},
    "headCoach": "Terry Brennan",
    "rankings": {"home": {"ap": 5}, "away": {"ap": 16}},
    "weather": {"icon": "cloudy", "temperature": 47}
  },
  {
    "result": "L",
    "isHomeGame": false,
    "date": "11/09/1957",
    "location": {
      "city": "East Lansing",
      "state": "MI",
      "stadium": "Spartan Stadium",
      "coordinates": [42.727122, -84.486078]
    },
    "opponentId": "MSU",
    "score": {"away": 6, "home": 34},
    "linescore": {"away": [], "home": []},
    "headCoach": "Terry Brennan",
    "rankings": {"away": {"ap": 15}, "home": {"ap": 4}}
  },
  {
    "result": "W",
    "isHomeGame": false,
    "date": "11/16/1957",
    "location": {
      "city": "Norman",
      "state": "OK",
      "stadium": "Oklahoma Memorial Stadium",
      "coordinates": [35.205196, -97.44276]
    },
    "opponentId": "OKLA",
    "score": {"away": 7, "home": 0},
    "linescore": {"away": [], "home": []},
    "headCoach": "Terry Brennan",
    "rankings": {"home": {"ap": 2}},
    "weather": {"icon": "partly-cloudy-night", "temperature": 50}
  },
  {
    "result": "L",
    "isHomeGame": true,
    "date": "11/23/1957",
    "opponentId": "IOWA",
    "score": {"away": 21, "home": 13},
    "linescore": {"away": [], "home": []},
    "headCoach": "Terry Brennan",
    "rankings": {"home": {"ap": 9}, "away": {"ap": 8}},
    "weather": {"icon": "clear-night", "temperature": 24}
  },
  {
    "result": "W",
    "isHomeGame": true,
    "date": "11/30/1957",
    "opponentId": "USC",
    "score": {"away": 12, "home": 40},
    "linescore": {"away": [], "home": []},
    "headCoach": "Terry Brennan",
    "rankings": {"home": {"ap": 12}},
    "weather": {"icon": "snow", "temperature": 29}
  },
  {
    "result": "W",
    "isHomeGame": false,
    "date": "12/07/1957",
    "location": {
      "city": "Dallas",
      "state": "TX",
      "stadium": "Cotton Bowl",
      "coordinates": [32.779494, -96.759724]
    },
    "opponentId": "SMU",
    "score": {"away": 54, "home": 21},
    "linescore": {"away": [], "home": []},
    "headCoach": "Terry Brennan",
    "rankings": {"away": {"ap": 12}},
    "weather": {"icon": "partly-cloudy-night", "temperature": 50}
  }
]
